{
    "version": "3.1.489.0",
    "description": "Easily backup, restore and transfer video games save data",
    "homepage": "https://www.gamesave-manager.com",
    "license": "Freeware",
    "url": "https://www.gamesave-manager.com/?s=download&guid=%7B4113402B-83A3-4B56-845E-387F990B24BF%7D&a=dl#/dl.7z",
    "hash": "md5:9a7ed360ea7f405f6f9cdf7753433bfc",
    "pre_install": "if (!(Test-Path \"$dir\\settings\")) { New-Item \"$dir\\settings\" -Type directory | Out-Null }",
    "persist": "settings",
    "bin": "gs_mngr_3.exe",
    "shortcuts": [
        [
            "gs_mngr_3.exe",
            "GameSave Manager"
        ]
    ],
    "checkver": {
        "regex": "(?sm)releasedetailsvalues\">\\s+([\\d\\.]+).*guid={(?<GUID>[\\w-]+)\\}\""
    },
    "autoupdate": {
        "url": "https://www.gamesave-manager.com/?s=download&guid=%7B$matchGUID%7D&a=dl#/dl.7z",
        "hash": {
            "url": "https://www.gamesave-manager.com/?s=download&guid=%7B$matchGUID%7D",
            "regex": "md5 checksum is <i>($md5)</i>"
        }
    }
}
